HISTORY.rst
README.rst
setup.cfg
setup.py
docs/INSTALL.txt
docs/LICENSE.GPL
docs/LICENSE.txt
sd/__init__.py
sd.analytics.egg-info/PKG-INFO
sd.analytics.egg-info/SOURCES.txt
sd.analytics.egg-info/dependency_links.txt
sd.analytics.egg-info/entry_points.txt
sd.analytics.egg-info/namespace_packages.txt
sd.analytics.egg-info/not-zip-safe
sd.analytics.egg-info/requires.txt
sd.analytics.egg-info/top_level.txt
sd/analytics/__init__.py
sd/analytics/browser.txt
sd/analytics/configure.zcml
sd/analytics/controlpanel-links.pt
sd/analytics/controlpanel.py
sd/analytics/interfaces.py
sd/analytics/settings.py
sd/analytics/tests.py
sd/analytics/transform.py
sd/analytics/transform.txt
sd/analytics/locales/sd.analytics.pot
sd/analytics/locales/da/LC_MESSAGES/sd.analytics.po