Metadata-Version: 1.1
Name: sd.analytics
Version: 0.1.3
Summary: Google analytics integration for Singing & Dancing
Home-page: http://www.headnet.dk
Author: Thomas Clement Mogensen
Author-email: thomas@headnet.dk
License: GPL
Keywords: google analytics singing dancing newsletter trackingaddon extension
Platform: UNKNOWN
Classifier: Environment :: Web Environment
Classifier: Framework :: Plone
Classifier: Framework :: Plone :: 4.3
Classifier: Programming Language :: Python
Classifier: Programming Language :: Python :: 2.7
